commonbase/__init__.py
commonbase/chat_context.py
commonbase/completion.py
commonbase/completion_response.py
commonbase/exceptions.py
commonbase/provider_config.py
commonbase/tests/__init__.py
commonbase/tests/test_chat_completion.py
commonbase/tests/test_completion.py
commonbase/tests/test_functions.py
commonbase/tests/test_model.py
commonbase/tests/test_provider_api_key.py
commonbase-0.4.1.dist-info/METADATA
commonbase-0.4.1.dist-info/WHEEL
commonbase-0.4.1.dist-info/licenses/LICENSE
commonbase-0.4.1.dist-info/RECORD
