Metadata-Version: 2.1
Name: commonbase
Version: 0.4.1
Summary: Commonbase Python SDK
Project-URL: Homepage, https://github.com/commonbaseapp/commonbase-python
Project-URL: Source, https://github.com/commonbaseapp/commonbase-python
Project-URL: Tracker, https://github.com/commonbaseapp/commonbase-python/issues
License: MIT License
License-File: LICENSE
Requires-Python: >=3.8
Requires-Dist: requests>=2.31.0
Requires-Dist: sseclient-py>=1.7.2
